ct_module/__init__.py
ct_module/test.py
ct_module-0.26.dist-info/METADATA
ct_module-0.26.dist-info/WHEEL
ct_module-0.26.dist-info/licence.txt
ct_module-0.26.dist-info/top_level.txt
ct_module-0.26.dist-info/RECORD
